[
  {
    "adcode": 440303,
    "name": "罗湖区",
    "center": [
      114.123885,
      22.555341
    ],
    "centroid": [
      114.148158,
      22.57487
    ],
    "level": "district",
    "parent": "440300"
  },
  {
    "adcode": 440304,
    "name": "福田区",
    "center": [
      114.05096,
      22.541009
    ],
    "centroid": [
      114.046594,
      22.543431
    ],
    "level": "district",
    "parent": "440300"
  },
  {
    "adcode": 440305,
    "name": "南山区",
    "center": [
      113.92943,
      22.531221
    ],
    "centroid": [
      113.94053,
      22.545584
    ],
    "level": "district",
    "parent": "440300"
  },
  {
    "adcode": 440306,
    "name": "宝安区",
    "center": [
      113.828671,
      22.754741
    ],
    "centroid": [
      113.856348,
      22.676207
    ],
    "level": "district",
    "parent": "440300"
  },
  {
    "adcode": 440307,
    "name": "龙岗区",
    "center": [
      114.251372,
      22.721511
    ],
    "centroid": [
      114.211562,
      22.692969
    ],
    "level": "district",
    "parent": "440300"
  },
  {
    "adcode": 440308,
    "name": "盐田区",
    "center": [
      114.235366,
      22.555069
    ],
    "centroid": [
      114.275663,
      22.594708
    ],
    "level": "district",
    "parent": "440300"
  },
  {
    "adcode": 440309,
    "name": "龙华区",
    "center": [
      114.044346,
      22.691963
    ],
    "centroid": [
      114.034788,
      22.684083
    ],
    "level": "district",
    "parent": "440300"
  },
  {
    "adcode": 440310,
    "name": "坪山区",
    "center": [
      114.338441,
      22.69423
    ],
    "centroid": [
      114.362823,
      22.689495
    ],
    "level": "district",
    "parent": "440300"
  },
  {
    "adcode": 440311,
    "name": "光明区",
    "center": [
      113.935895,
      22.748816
    ],
    "centroid": [
      113.931239,
      22.763198
    ],
    "level": "district",
    "parent": "440300"
  }
]